EyesLibrary/__init__.py
EyesLibrary/version.py
EyesLibrary/keywords/__init__.py
EyesLibrary/keywords/check.py
EyesLibrary/keywords/session.py
EyesLibrary/keywords/target.py
EyesLibrary/resources/__init__.py
EyesLibrary/resources/utils.py
EyesLibrary/resources/variables.py
robotframework_eyeslibrary-2.1.dist-info/LICENSE.txt
robotframework_eyeslibrary-2.1.dist-info/METADATA
robotframework_eyeslibrary-2.1.dist-info/WHEEL
robotframework_eyeslibrary-2.1.dist-info/top_level.txt
robotframework_eyeslibrary-2.1.dist-info/RECORD
