Metadata-Version: 2.1
Name: robotframework-eyeslibrary
Version: 2.1
Summary: Visual verification testing library for Robot Framework
Home-page: https://github.com/joel-oliveira/EyesLibrary
Author: Joel Oliveira, Sofia Nunes
Author-email: <joel.oliveira@criticalsoftware.com>, <sofia.nunes@criticalsoftware.com>
License: Apache License 2.0
Keywords: robotframework testing testautomation eyes-selenium selenium appium visual-verification
Platform: any
Classifier: License :: OSI Approved :: Apache Software License
Classifier: Programming Language :: Python :: 2.7
Classifier: Programming Language :: Python :: 3.6
Classifier: Development Status :: 5 - Production/Stable
Classifier: Intended Audience :: Developers
Classifier: Framework :: Robot Framework :: Library
Classifier: Topic :: Software Development :: Testing
Classifier: Topic :: Software Development :: Quality Assurance
Requires-Dist: robotframework (<4,>3.0)
Requires-Dist: eyes-selenium (<4,>=3.16.2)
Requires-Dist: six (<2,>1.0.0)
Requires-Dist: robotframework-seleniumlibrary
Requires-Dist: robotframework-appiumlibrary
